DeepSaki/__init__.py
DeepSaki/activations/__init__.py
DeepSaki/activations/complex_valued_activations.py
DeepSaki/augmentations/__init__.py
DeepSaki/augmentations/grid_cutting.py
DeepSaki/constraints/__init__.py
DeepSaki/constraints/constraints.py
DeepSaki/initializers/__init__.py
DeepSaki/initializers/complex_initializer.py
DeepSaki/initializers/he_alpha.py
DeepSaki/layers/__init__.py
DeepSaki/layers/fourier_layer.py
DeepSaki/layers/layer_composites.py
DeepSaki/layers/layer_helper.py
DeepSaki/layers/padding.py
DeepSaki/layers/pooling.py
DeepSaki/layers/sub_model_composites.py
DeepSaki/losses/__init__.py
DeepSaki/losses/image_based_losses.py
DeepSaki/models/__init__.py
DeepSaki/models/autoencoders.py
DeepSaki/models/discriminators.py
DeepSaki/optimizers/__init__.py
DeepSaki/optimizers/swats.py
DeepSaki/types/__init__.py
DeepSaki/types/layers_enums.py
DeepSaki/types/losses_enums.py
DeepSaki/types/optimizers_enums.py
DeepSaki/utils/__init__.py
DeepSaki/utils/environment.py
DeepSaki-1.0.1.dist-info/LICENSE
DeepSaki-1.0.1.dist-info/METADATA
DeepSaki-1.0.1.dist-info/WHEEL
DeepSaki-1.0.1.dist-info/top_level.txt
DeepSaki-1.0.1.dist-info/RECORD
