Metadata-Version: 2.1
Name: DeepSaki
Version: 1.0.1
Summary: DeepSaki is an add-on to TensorFlow. It provides a variaty of custom classes ranging from activation functions to entire models, helper functions to facilitate connectiong to your, compute HW and many more!
Author-email: Sascha Kirch <susch130993@googlemail.com>
Maintainer-email: Sascha Kirch <susch130993@googlemail.com>
License: MIT License
Project-URL: Homepage, https://sascha-kirch.github.io/
Project-URL: Documentation, https://sascha-kirch.github.io/DeepSaki
Project-URL: Repository, https://github.com/sascha-kirch/DeepSaki
Project-URL: Changelog, https://sascha-kirch.github.io/DeepSaki/latest/CHANGELOG/
Keywords: deeplearning,machinelearning,tensorflow,TPU
Platform: unix
Platform: linux
Platform: osx
Platform: cygwin
Platform: win32
Classifier: Programming Language :: Python :: 3
Classifier: Programming Language :: Python :: 3
Classifier: Programming Language :: Python :: 3.10
Classifier: Programming Language :: Python :: 3.11
Classifier: Programming Language :: Python :: 3.12
Classifier: Programming Language :: Python :: 3.13
Classifier: Operating System :: Microsoft :: Windows
Classifier: Operating System :: POSIX :: Linux
Classifier: Operating System :: POSIX
Classifier: Operating System :: Unix
Classifier: Operating System :: MacOS
Classifier: Development Status :: 5 - Production/Stable
Classifier: Intended Audience :: Science/Research
Classifier: Topic :: Scientific/Engineering :: Artificial Intelligence
Requires-Python: >=3.10
License-File: LICENSE
Requires-Dist: tensorflow >=2.8
Requires-Dist: numpy >=1.21.6
Requires-Dist: tensorflow-addons >=0.21.0
Requires-Dist: pandas
Requires-Dist: matplotlib
Requires-Dist: pydot
Requires-Dist: opencv-contrib-python
Requires-Dist: einops
